gestures-0.1.0.dist-info/DESCRIPTION.rst
gestures-0.1.0.dist-info/METADATA
gestures-0.1.0.dist-info/RECORD
gestures-0.1.0.dist-info/WHEEL
gestures-0.1.0.dist-info/metadata.json
gestures-0.1.0.dist-info/top_level.txt
microsoft/__init__.py
microsoft/gestures/__init__.py
microsoft/gestures/all_fingers_context.py
microsoft/gestures/any_finger_context.py
microsoft/gestures/any_hand_context.py
microsoft/gestures/finger.py
microsoft/gestures/finger_flexion.py
microsoft/gestures/finger_pose.py
microsoft/gestures/fingertip_distance_relation.py
microsoft/gestures/fingertip_placement_relation.py
microsoft/gestures/gesture.py
microsoft/gestures/gesture_container.py
microsoft/gestures/gesture_segment.py
microsoft/gestures/hand_motion.py
microsoft/gestures/hand_part_motion.py
microsoft/gestures/hand_pose.py
microsoft/gestures/motion_script.py
microsoft/gestures/motion_segment.py
microsoft/gestures/palm_motion.py
microsoft/gestures/palm_pose.py
microsoft/gestures/pass_through_gesture_segment.py
microsoft/gestures/pose_constraint.py
microsoft/gestures/pose_direction.py
microsoft/gestures/relative_distance.py
microsoft/gestures/relative_placement.py
microsoft/gestures/version.py
microsoft/gestures/vertical_motion_script.py
microsoft/gestures/vertical_motion_segment.py
microsoft/gestures/endpoint/__init__.py
microsoft/gestures/endpoint/gesture_service_endpoint.py
microsoft/gestures/endpoint/gestures_service_endpoint_factory.py
microsoft/gestures/logging/__init__.py
microsoft/gestures/protocol/__init__.py
microsoft/gestures/protocol/client_command.py
microsoft/gestures/protocol/client_info.py
microsoft/gestures/protocol/gestures_protocol.py
microsoft/gestures/protocol/gestures_request.py
microsoft/gestures/protocol/serialization_utils.py
