Metadata-Version: 2.0
Name: gestures
Version: 0.1.0
Summary: Microsoft Gestures SDK
Home-page: https://github.com/Microsoft/Gestures-Samples
Author: Danny Shemesh
Author-email: dashemes@microsoft.com
License: MIT
Keywords: microsoft gestures project prague
Platform: UNKNOWN
Classifier: Development Status :: 3 - Alpha
Classifier: Intended Audience :: Developers
Classifier: Topic :: Software Development :: Build Tools
Classifier: License :: OSI Approved :: MIT License
Classifier: Programming Language :: Python :: 2
Classifier: Programming Language :: Python :: 2.7
Classifier: Programming Language :: Python :: 3
Classifier: Programming Language :: Python :: 3.3
Classifier: Programming Language :: Python :: 3.4
Classifier: Programming Language :: Python :: 3.5
Requires-Dist: dicttoxml
Requires-Dist: psutil
Requires-Dist: requests
